setup.py
swnamer/__init__.py
swnamer/collections.py
swnamer/generator.py
swnamer/version.py
swnamer.egg-info/PKG-INFO
swnamer.egg-info/SOURCES.txt
swnamer.egg-info/dependency_links.txt
swnamer.egg-info/entry_points.txt
swnamer.egg-info/requires.txt
swnamer.egg-info/top_level.txt
tests/__init__.py
tests/base.py
tests/test_generator.py
tests/test_version.py