Metadata-Version: 1.1
Name: swnamer
Version: 0.1.0
Summary: swnamer is a name generator that uses Star Wars characters, species and planets to create unique names.
Home-page: https://github.com/heynemann/swnamer
Author: Bernardo Heynemann
Author-email: heynemann@gmail.com
License: MIT
Keywords: name python star wars
Platform: UNKNOWN
Classifier: Development Status :: 4 - Beta
Classifier: Intended Audience :: Developers
Classifier: License :: OSI Approved :: MIT License
Classifier: Natural Language :: English
Classifier: Operating System :: Unix
Classifier: Programming Language :: Python :: 2.7
Classifier: Programming Language :: Python :: 3.4
Classifier: Programming Language :: Python :: Implementation :: PyPy
Classifier: Operating System :: OS Independent
